pyqvrpro/__init__.py
pyqvrpro/client.py
pyqvrpro-0.52.dist-info/LICENSE.txt
pyqvrpro-0.52.dist-info/METADATA
pyqvrpro-0.52.dist-info/WHEEL
pyqvrpro-0.52.dist-info/top_level.txt
pyqvrpro-0.52.dist-info/RECORD
